pepkordna/__init__.py
pepkordna/operators/__init__.py
pepkordna/operators/audit_base_operator.py
pepkordna/operators/audit_duplicates.py
pepkordna/operators/audit_trend_analysis.py
pepkordna/utils/__init__.py
pepkordna/utils/utils.py
pepkordna-0.111.dist-info/METADATA
pepkordna-0.111.dist-info/WHEEL
pepkordna-0.111.dist-info/top_level.txt
pepkordna-0.111.dist-info/RECORD
