Metadata-Version: 2.1
Name: pepkordna
Version: 0.111
Summary: Utils and airflow operators for Pepkor DNA data engineering team
Home-page: UNKNOWN
Author: Pepkor - Data and Analytics
Maintainer: Pepkor - Data and Analytics
License: UNKNOWN
Platform: UNKNOWN
Classifier: Operating System :: OS Independent
Classifier: Programming Language :: Python :: 3
Requires-Python: >=3.7
